fast_walk-0.1.5.dist-info/METADATA
fast_walk-0.1.5.dist-info/WHEEL
fast_walk-0.1.5.dist-info/licenses/LICENSE
fast_walk/__init__.py
fast_walk/__init__.pyi
fast_walk/fast_walk.cpython-313t-aarch64-linux-gnu.so
fast_walk/py.typed
fast_walk-0.1.5.dist-info/RECORD
