Metadata-Version: 2.4
Name: fast-walk
Version: 0.1.5
Classifier: Programming Language :: Rust
Classifier: Programming Language :: Python :: Implementation :: CPython
Classifier: Programming Language :: Python :: Implementation :: PyPy
Classifier: Programming Language :: Python :: 3
Classifier: Programming Language :: Python :: 3.13
Classifier: Programming Language :: Python :: 3.14
Classifier: Programming Language :: Python :: 3 :: Only
License-File: LICENSE
Summary: A fast reimplementation of ast.walk()
License: MIT
Requires-Python: >=3.13
